libra-core/__init__.py
libra-core/apollo_config.py
libra-core/config.py
libra-core/local_config.py
libra_core/__init__.py
libra_core/apollo_client.py
libra_core/apollo_config.py
libra_core/config.py
libra_core/influxd.py
libra_core/local_config.py
libra_core/log.py
libra_core/log_id.py
libra_core/message.py
libra_core/rabbitmq.py
libra_core/utils.py
libra_core/wrapper.py
libra_core_py-0.0.26.dist-info/METADATA
libra_core_py-0.0.26.dist-info/WHEEL
libra_core_py-0.0.26.dist-info/top_level.txt
libra_core_py-0.0.26.dist-info/RECORD
